fid/__init__.py
fid/__main__.py
fid/commands.py
fid/config.py
fid/fid.py
fid/models.py
fid/tui.py
fid/utils.py
fid-0.2.1.dist-info/licenses/LICENSE
fid-0.2.1.dist-info/METADATA
fid-0.2.1.dist-info/WHEEL
fid-0.2.1.dist-info/entry_points.txt
fid-0.2.1.dist-info/top_level.txt
fid-0.2.1.dist-info/RECORD
