Metadata-Version: 2.4
Name: fid
Version: 0.2.1
Summary: Add your description here
License: MIT
Project-URL: Homepage, https://github.com/chamanbravo/fid
Project-URL: Repository, https://github.com/chamanbravo/fid
Project-URL: Issues, https://github.com/chamanbravo/fid/issues
Classifier: Development Status :: 4 - Beta
Classifier: Intended Audience :: Information Technology
Classifier: Intended Audience :: System Administrators
Classifier: Operating System :: OS Independent
Classifier: Programming Language :: Python
Classifier: Topic :: Software Development :: Libraries :: Application Frameworks
Classifier: Topic :: Software Development :: Libraries :: Python Modules
Classifier: Topic :: Software Development :: Libraries
Classifier: Topic :: Software Development
Classifier: Typing :: Typed
Classifier: Intended Audience :: Developers
Classifier: License :: OSI Approved :: MIT License
Classifier: Programming Language :: Python :: 3.10
Classifier: Programming Language :: Python :: 3.11
Classifier: Programming Language :: Python :: 3.12
Classifier: Programming Language :: Python :: 3.13
Classifier: Programming Language :: Python :: 3.14
Requires-Python: >=3.10
License-File: LICENSE
Requires-Dist: typer
Requires-Dist: rich
Requires-Dist: pydantic-ai
Requires-Dist: readchar
Requires-Dist: textual
Provides-Extra: pre-commit
Requires-Dist: pre-commit; extra == "pre-commit"
Dynamic: license-file
